pwpy_db/__init__.py
pwpy_db/trino_connector.py
pwpy_db-0.1.13.dist-info/licenses/LICENSE
pwpy_db-0.1.13.dist-info/METADATA
pwpy_db-0.1.13.dist-info/WHEEL
pwpy_db-0.1.13.dist-info/top_level.txt
pwpy_db-0.1.13.dist-info/RECORD
