Metadata-Version: 2.4
Name: pwpy_db
Version: 0.1.13
Summary: Secure Trino connector for Python with pandas output
Home-page: https://github.com/kamlesh1114/pwpy_db
Author: Kamlesh Kumar
Author-email: kamlesh.kumar2@pw.live
Classifier: Programming Language :: Python :: 3
Classifier: License :: OSI Approved :: MIT License
Classifier: Operating System :: OS Independent
Requires-Python: >=3.8
License-File: LICENSE
Requires-Dist: trino>=0.319
Requires-Dist: pandas>=1.0
Requires-Dist: python-dotenv>=1.0
Requires-Dist: psutil>=5.9
Requires-Dist: requests>=2.20
Dynamic: author
Dynamic: author-email
Dynamic: classifier
Dynamic: description-content-type
Dynamic: home-page
Dynamic: license-file
Dynamic: requires-dist
Dynamic: requires-python
Dynamic: summary
